{
 "196": {
  "sci": {
   "takhreej": "أخرجه مسلم (55)",
   "hukm": "صحيح"
  },
  "local": {
   "nasai": [
    "4197",
    "4198",
    "4199",
    "4200"
   ]
  },
  "muh": [
   "3029"
  ],
  "d": "06.06.2026"
 },
 "677": {
  "sci": {
   "takhreej": "أخرجه البخاري (1361) باختلاف يسير",
   "hukm": "[صحيح]"
  },
  "local": {
   "bukhari": [
    "218",
    "1361"
   ],
   "abudawud": [
    "20"
   ],
   "ibnmajah": [
    "347",
    "349"
   ],
   "nasai": [
    "2069"
   ],
   "nasaikubra": [
    "2207"
   ]
  },
  "muh": [],
  "d": "06.06.2026"
 },
 "78": {
  "sci": {
   "takhreej": "أخرجه مسلم (78)، والنسائي في ((الكبرى)) (8097) واللفظ لهما، والترمذي (3736) باختلاف يسير.",
   "hukm": "غريب عن شعبة ، والمشهور حديث الأعمش"
  },
  "local": {
   "abuawana": [
    "55"
   ]
  },
  "muh": [],
  "d": "06.06.2026"
 },
 "2363": {
  "sci": {
   "takhreej": "أخرجه أحمد (12544)، وأبو يعلى (3480)، وابن حبان (22) جميعهم بلفظ مقارب  ⸱  أخرجه ابن شاهين في ((شرح مذاهب أهل السنة)) (168)، والحاكم (2718)، وابن عساكر (30/ 111) واللفظ لهم، وأحمد (16577) مطولا.  ⸱  أخرجه أحمد (16577)، والطبراني (5/ 59) (4578)، وأبو داود الطيالسي في ((المسند)) (1269) بنحوه.  ⸱  -  ⸱  أخرجه الطبراني في ((الأوسط)) (8764) واللفظ له، والبخاري (5191)، ومسلم (1479) بنحوه.  ⸱  أخرجه البخاري (5191)، ومسلم (1479)، والترمذي (3318) بنحوه.",
   "hukm": "[صحيح]"
  },
  "local": {},
  "muh": [
   "1539"
  ],
  "d": "07.06.2026"
 },
 "1508": {
  "sci": {
   "takhreej": "أخرجه الترمذي (2127) مطولا، وأحمد (1037) كلاهما بلفظه، ومسلم (1370) بنحوه، وأبو داود (4530) مختصرا.  ⸱  أخرجه البخاري (3179)، ومسلم (1370)، وأبو داود (2034)، والنسائي في ((السنن الكبرى)) (8681)، وأحمد (1037) واللفظ له  ⸱  أخرجه أبو يعلى (955) واللفظ له، والحاكم (7807) باختلاف يسير، والبخاري (3198)، ومسلم (1610) بالفقرة الأولى فقط.  ⸱  أخرجه البخاري (2452)، ومسلم (1610)، والترمذي (1418) مختصراً، وأحمد (1649) واللفظ له  ⸱  أخرجه البخاري (1870)، وأبو داود (2034)، وأحمد (1037) جميعا بلفظه، ومسلم (1370)، والترمذي (2127)  كلاهما بنحوه",
   "hukm": "[صحيح]"
  },
  "local": {
   "muslim": [
    "1371"
   ],
   "muqbil": [
    "3312"
   ]
  },
  "muh": [],
  "d": "08.06.2026"
 },
 "7": {
  "sci": {
   "takhreej": "أخرجه مسلم (2477) بلفظ: \"اللهم فقهه\"  ⸱  أخرجه مسلم (1182)  ⸱  أخرجه أحمد (19114)، وابن أبي شيبة (33422)، وابن أبي عاصم في ((الجهاد)) (1/ 139)، والبزار (3358) واللفظ لهم جميعا.  ⸱  أخرجه مسلم (635)  ⸱  أخرجه مسلم (2239)، وابن ماجه (3230)، وأحمد (24568)، وأبو عوانة (9899) واللفظ لهم جميعا.  ⸱  أخرجه مسلم (1526) باختلاف يسير  ⸱  أخرجه مسلم (1098)  ⸱  من أفراد البخاري على مسلم  ⸱  أخرجه البخاري (5352)، ومسلم (993)  ⸱  أخرجه مسلم (2226) باختلاف يسير  ⸱  أخرجه مسلم (626)  ⸱  أخرجه مسلم (607) باختلاف يسير  ⸱  أخرجه مسلم (279) باختلاف يسير  ⸱  أخرجه النسائي (4161)، والشاشي في ((المسند)) (1231)، والطبراني في ((مسند الشاميين)) (3197)، وابن منده في ((الإيمان)) (47) واللفظ لهم مطولا.  ⸱  أخرجه مسلم (1583) باختلاف يسير  ⸱  أخرجه مسلم (33) باختلاف يسير  ⸱  أخرجه مسلم (2950)، البيهقي في ((شعب الإيمان)) ",
   "hukm": "[صحيح]"
  },
  "local": {
   "bukhari": [
    "{'n': '14', ",
    "{'n': '18', ",
    "{'n': '25', ",
    "{'n': '37', ",
    "{'n': '47', ",
    "{'n': '54', ",
    "{'n': '56', ",
    "{'n': '66', "
   ],
   "muslim": [
    "{'n': '2', '",
    "{'n': '18', ",
    "{'n': '21', ",
    "{'n': '33', ",
    "{'n': '46', ",
    "{'n': '47', ",
    "{'n': '50', ",
    "{'n': '52', "
   ],
   "abudawud": [
    "{'n': '6', '",
    "{'n': '25', ",
    "{'n': '40', ",
    "{'n': '54', ",
    "{'n': '65', ",
    "{'n': '73', ",
    "{'n': '75', ",
    "{'n': '76', "
   ],
   "tirmidhi": [
    "{'n': '39', ",
    "{'n': '51', ",
    "{'n': '74', ",
    "{'n': '75', ",
    "{'n': '92', ",
    "{'n': '124',",
    "{'n': '150',",
    "{'n': '195',"
   ],
   "ibnmajah": [
    "{'n': '7', '",
    "{'n': '8', '",
    "{'n': '10', ",
    "{'n': '12', ",
    "{'n': '13', ",
    "{'n': '14', ",
    "{'n': '16', ",
    "{'n': '46', "
   ],
   "nasai": [
    "{'n': '1', '",
    "{'n': '7', '",
    "{'n': '9', '",
    "{'n': '12', ",
    "{'n': '24', ",
    "{'n': '34', ",
    "{'n': '43', ",
    "{'n': '44', "
   ],
   "malik": [
    "{'n': '5', '",
    "{'n': '15', ",
    "{'n': '21', ",
    "{'n': '27', ",
    "{'n': '28', ",
    "{'n': '29', ",
    "{'n': '30', ",
    "{'n': '33', "
   ],
   "ahmad": [
    "{'n': '18', ",
    "{'n': '85', ",
    "{'n': '118',",
    "{'n': '133',",
    "{'n': '154',",
    "{'n': '172',",
    "{'n': '173',",
    "{'n': '270',"
   ],
   "muqbil": [
    "{'n': '36', ",
    "{'n': '66', ",
    "{'n': '224',",
    "{'n': '247',",
    "{'n': '488',",
    "{'n': '593',",
    "{'n': '802',",
    "{'n': '851',"
   ],
   "ibnmubarak": [
    "{'n': '34', ",
    "{'n': '80', ",
    "{'n': '205',",
    "{'n': '245',",
    "{'n': '247',"
   ],
   "ismail": [
    "{'n': '41', ",
    "{'n': '52', ",
    "{'n': '56', ",
    "{'n': '88', ",
    "{'n': '132',",
    "{'n': '137',",
    "{'n': '142',",
    "{'n': '143',"
   ],
   "adabmufrad": [
    "{'n': '38', ",
    "{'n': '41', ",
    "{'n': '43', ",
    "{'n': '50', ",
    "{'n': '56', ",
    "{'n': '65', ",
    "{'n': '79', ",
    "{'n': '81', "
   ],
   "humaydi": [
    "{'n': '13', ",
    "{'n': '28', ",
    "{'n': '33', ",
    "{'n': '71', ",
    "{'n': '85', ",
    "{'n': '90', ",
    "{'n': '113',",
    "{'n': '119',"
   ],
   "abdbinhumayd": [
    "{'n': '128',",
    "{'n': '221',",
    "{'n': '344',",
    "{'n': '365',",
    "{'n': '529',",
    "{'n': '530',",
    "{'n': '571',",
    "{'n': '656',"
   ],
   "ibnaljad": [
    "{'n': '146',",
    "{'n': '266',",
    "{'n': '871',",
    "{'n': '937',",
    "{'n': '1062'",
    "{'n': '1075'",
    "{'n': '1216'",
    "{'n': '1289'"
   ],
   "ishaq": [
    "{'n': '5', '",
    "{'n': '6', '",
    "{'n': '8', '",
    "{'n': '9', '",
    "{'n': '10', ",
    "{'n': '17', ",
    "{'n': '18', ",
    "{'n': '19', "
   ],
   "tayalisi": [
    "{'n': '1', '",
    "{'n': '2', '",
    "{'n': '39', ",
    "{'n': '61', ",
    "{'n': '73', ",
    "{'n': '74', ",
    "{'n': '75', ",
    "{'n': '83', "
   ],
   "darimi": [
    "{'n': '9', '",
    "{'n': '13', ",
    "{'n': '55', ",
    "{'n': '236',",
    "{'n': '241',",
    "{'n': '275',",
    "{'n': '277',",
    "{'n': '283',"
   ],
   "ibnkhuzayma": [
    "{'n': '4', '",
    "{'n': '8', '",
    "{'n': '72', ",
    "{'n': '75', ",
    "{'n': '94', ",
    "{'n': '99', ",
    "{'n': '102',",
    "{'n': '104',"
   ]
  },
  "muh": [
   "184",
   "1846",
   "2977",
   "1",
   "4",
   "13",
   "15",
   "34",
   "35",
   "37",
   "39"
  ],
  "d": "12.06.2026"
 }
}