{"53772":{"reps":" رواه احمد\"، ثم ذكر لفظا اخر نسبه للطبراني في الاوسط، ثم","items":[{"b":"98139","h":6999,"p":3234},{"b":"28107","h":2083,"p":2500}]},"53787":{"reps":" \"ياتي علي الناس زمان يغربلون فيه غربله، يبقي منهم حثاله، قد","items":[{"b":"98139","h":7049,"p":3267},{"b":"907","h":3594,"p":4743}]},"53848":{"reps":" \"لا تاتوا الصلاه وانتم تسعون، واتوها وعليكم السكينه، فما ادركتم فصلوا","items":[{"b":"98139","h":7229,"p":3424},{"b":"98139","h":7251,"p":3442},{"b":"18144","h":1276,"p":1878}]},"53855":{"reps":" اكل بعضي بعضا، فاذن لها بنفسين، نفس في الشتاء، ونفس في","items":[{"b":"98139","h":7246,"p":3439},{"b":"8493","h":972,"p":1097}]},"53867":{"reps":" \"كان ثقه عاليا رفيعا فقيها، كثير الحديث\". والحديث رواه البخاري (١٠:","items":[{"b":"98139","h":7273,"p":3461},{"b":"8361","h":1097,"p":1725}]},"53893":{"reps":"انتعل احدكم فليبدا باليمين وخلع اليسري، واذا انقطع شسع احدكم فلا يمش","items":[{"b":"98139","h":7343,"p":3514},{"b":"18144","h":9125,"p":10763}]},"53901":{"reps":" ابي هريره، عن النبي -صلي الله عليه وسلم -: \"تسموا باسمي،","items":[{"b":"98139","h":7371,"p":3541},{"b":"8361","h":56,"p":95}]},"53906":{"reps":"بكر، عن عمر بن عبد العزيز، عن ابي بكر ابن عبد الرحمن،","items":[{"b":"98139","h":7384,"p":3551},{"b":"98139","h":7634,"p":3730},{"b":"8361","h":7990,"p":11105}]},"53959":{"reps":" \"كان رجل يداين الناس، فكان يقول لفتاه: اذا اتيت معسرا فتجاوز","items":[{"b":"98139","h":7569,"p":3694},{"b":"98139","h":8369,"p":4177},{"b":"1376","h":3480,"p":5338}]},"53973":{"reps":" \"اذا اقيمت الصلاه فلا تاتوها تسعون، ولكن ائتوها وانتم تمشون، وعليكم","items":[{"b":"98139","h":7649,"p":3740},{"b":"1339","h":866,"p":731},{"b":"18144","h":1381,"p":1994},{"b":"18144","h":1402,"p":2018}]},"53987":{"reps":" \"ما من مولود الا الشيطان يمسه حين يولد، فيستهل صارخا من","items":[{"b":"98139","h":7694,"p":3775},{"b":"18144","h":11654,"p":13526}]},"54003":{"reps":" \"من ادرك من الصلاه ركعه فقد ادرك الصلاه\"","items":[{"b":"98139","h":7752,"p":3819},{"b":"121382","h":1849,"p":887}]},"54017":{"reps":" \"ان في الجمعه ساعه لا يوافقها عبد مسلم يسال الله فيها","items":[{"b":"98139","h":7810,"p":3848},{"b":"98139","h":7811,"p":3848},{"b":"8361","h":10233,"p":14034}]},"54047":{"reps":" لينتهين رجال ممن حول المسجد لا يشهدون العشاء الاخره في الجميع،","items":[{"b":"98139","h":7903,"p":3909},{"b":"4407","h":2809,"p":2638}]},"54049":{"reps":" \"من اتاه الله من هذا المال شيئا من غير ان يساله","items":[{"b":"98139","h":7908,"p":3913},{"b":"10631","h":43,"p":82}]},"54061":{"reps":" \"كتبت عنه مع ابي، وهو صدوق\". وله ترجمه في تاريخ بغداد","items":[{"b":"98139","h":7933,"p":3946},{"b":"18144","h":12223,"p":14155}]},"54079":{"reps":" \"نزل القران علي سبعه احرف، المراء في القران كفر، ثلاث مرات،","items":[{"b":"98139","h":7976,"p":3986},{"b":"333","h":32121,"p":36916}]},"54088":{"reps":" \"هل ترون قبلتي، ها هنا؟، فوالله ما يخفي علي خشوعكم ولا","items":[{"b":"98139","h":8011,"p":4006},{"b":"1376","h":418,"p":704},{"b":"1376","h":2980,"p":4675},{"b":"735","h":408,"p":713},{"b":"735","h":2818,"p":4781}]},"54089":{"reps":" \"ما يصيب المؤمن من وصب ولا نصب ولا هم ولا حزن","items":[{"b":"98139","h":8014,"p":4009},{"b":"1376","h":5641,"p":8416}]},"54098":{"reps":" \"اذا سمعتم صياح الديكه من الليل فانما رات ملكا، سلو الله","items":[{"b":"98139","h":8050,"p":4028},{"b":"907","h":3303,"p":4338},{"b":"8361","h":10714,"p":14619}]},"54101":{"reps":" \"لم يتكلم في المهد الا ثلاثه: عيسي ابن مريم ﵇، وصبي","items":[{"b":"98139","h":8058,"p":4033},{"b":"907","h":3436,"p":4553}]},"54131":{"reps":" الله ﷺ \" [قال الله،: اذا تحدث عبدي بان يعمل حسنه","items":[{"b":"98139","h":8151,"p":4096},{"b":"18144","h":308,"p":775}]},"54157":{"reps":" الله ﷺ: \"والله لان يلج احدكم بيمينه فيP\u000f= \"ثم تكون\": لفظ","items":[{"b":"98139","h":8193,"p":4115},{"b":"907","h":6625,"p":9210}]},"54166":{"reps":" الله ﷺ: \"لا يقبل الله صلاه احدكم اذا احدث حتي يتوضا\"","items":[{"b":"98139","h":8206,"p":4121},{"b":"18144","h":706,"p":1220},{"b":"18144","h":9017,"p":10643},{"b":"13028","h":403,"p":423}]},"54182":{"reps":" الله ﷺ: \"انا اولي الناس بعيسي بن مريم في الاولي والاخره\"،","items":[{"b":"98139","h":8231,"p":4130},{"b":"18144","h":10484,"p":12250}]},"54225":{"reps":" الله ﷺ: \"ما منكم احد يدخله عملهP = حديث عبد الله","items":[{"b":"98139","h":8312,"p":4158},{"b":"8361","h":617,"p":925}]},"54256":{"reps":" \"يدخل الجنه اقوام افئدتهم مثل افئده الطير\"","items":[{"b":"98139","h":8364,"p":4176},{"b":"18144","h":12404,"p":14350}]},"54267":{"reps":" \"ما من مؤمن الا وانا اولي به في الدنيا والاخره، اقراوا","items":[{"b":"98139","h":8399,"p":4186},{"b":"907","h":2399,"p":3081}]}}