{"21504":{"reps":" لا ازال احب بني تميم بعد ثلاث ⦗٤٩٤⦘: سمعت رسول الله","items":[{"b":"12520","h":6108,"p":6125},{"b":"181","h":6108,"p":4945},{"b":"1376","h":2543,"p":4000},{"b":"1376","h":4366,"p":6320},{"b":"735","h":2405,"p":4090},{"b":"735","h":4108,"p":6438},{"b":"907","h":2543,"p":3283}]},"21510":{"reps":" كتب به الي منصور وقراته عليه قال: حدثني ابو عثمان مولي","items":[{"b":"12520","h":6141,"p":6158},{"b":"181","h":6141,"p":4967}]},"21513":{"reps":" دخلت يوما السوق مع رسول الله ﷺ فجلس الي البزارين، فاشتري","items":[{"b":"12520","h":6162,"p":6179},{"b":"181","h":6162,"p":4983}]},"21517":{"reps":" اخذ رجل من الانصار الشفره، والنبي ﷺ في بيت الانصاري، فقال","items":[{"b":"12520","h":6177,"p":6196},{"b":"181","h":6177,"p":4994}]},"21525":{"reps":"ان رسول الله ﷺ وابا بكر وعمر وعثمان كانوا يفتتحون القراءه ب»:","items":[{"b":"12520","h":6221,"p":6245},{"b":"181","h":3521,"p":2911},{"b":"654","h":2715,"p":3698}]},"21530":{"reps":"شر الطعام طعام الوليمه، يدعي اليها الاغنياء ويترك المساكين، ومن لم يات","items":[{"b":"12520","h":6250,"p":6277},{"b":"8140","h":1692,"p":1650}]},"21539":{"reps":" «لتاخذن كما اخذت الامم قبلكم ذراعا بذراع، وشبرا بشبر، وباعا بباع،","items":[{"b":"12520","h":6292,"p":6319},{"b":"181","h":6290,"p":5095}]},"21545":{"reps":" «لا يبع احدكم علي بيع اخيه، ولا يخطب علي خطبه اخيه،","items":[{"b":"12520","h":6317,"p":6344},{"b":"181","h":5884,"p":4783},{"b":"181","h":6316,"p":5111},{"b":"98139","h":4722,"p":2049},{"b":"98139","h":6411,"p":2793}]},"21547":{"reps":" «انما الامام جنه يقاتل من ورائه، فان هو اتقي وعدل كان","items":[{"b":"12520","h":6341,"p":6368},{"b":"181","h":6341,"p":5123}]},"21549":{"reps":" هلكت قال: «وما ذاك؟» ⦗٢٥٠⦘، قال: غشيت امراتي في رمضان، قال:","items":[{"b":"12520","h":6368,"p":6394},{"b":"181","h":6367,"p":5145}]},"21557":{"reps":" «لا تزال عصابه من امتي يقاتلون علي ابواب دمشق، وما حوله","items":[{"b":"12520","h":6417,"p":6444},{"b":"181","h":6417,"p":5194}]},"21559":{"reps":" كان ابي يصلي خلف ابي هريره بالمدينه قال: وكانت صلاته نحوا","items":[{"b":"12520","h":6422,"p":6449},{"b":"181","h":6421,"p":5199}]},"21569":{"reps":" من اذن بجنازه فانصرف عنها الي اهله كان له قيراط، فاذا","items":[{"b":"12520","h":6453,"p":6480},{"b":"181","h":6452,"p":5225}]},"21574":{"reps":" كنت امشي مع ابي هريره الي المسجد فمرت به امراه عاطره","items":[{"b":"12520","h":6479,"p":6506},{"b":"181","h":6479,"p":5254}]},"21576":{"reps":" «لا يدخل الجنه من لا يامن جاره بوائقه» [حكم حسين سليم","items":[{"b":"12520","h":6490,"p":6517},{"b":"1733","h":6668,"p":8214},{"b":"748","h":8152,"p":2732}]},"21585":{"reps":" «اذا بلغ بنو ابي العاص ثلاثين، كان دين الله دخلا، ومال","items":[{"b":"12520","h":6523,"p":6549},{"b":"181","h":6521,"p":5270}]},"21592":{"reps":" جاء الي النبي ﷺ اعرابي فاعجبه صحته وجلده فقال له رسول","items":[{"b":"12520","h":6556,"p":6581},{"b":"181","h":6555,"p":5295},{"b":"1733","h":13566,"p":15801},{"b":"98139","h":8780,"p":4300}]},"21593":{"reps":" «اكرمهم عند الله ﷿ اتقاهم»، قالوا: فغير هذا نسالك يا رسول","items":[{"b":"12520","h":6562,"p":6587},{"b":"181","h":6562,"p":5301}]},"21594":{"reps":" «ارجع فصل فانك لم تصل»، حتي فعل ذلك ثلاث مرات، فقال","items":[{"b":"12520","h":6577,"p":6600},{"b":"121382","h":460,"p":257}]},"21596":{"reps":" جلس رجلان عند رسول الله ﷺ احدهما اشرف من الاخر، فعطس","items":[{"b":"12520","h":6592,"p":6615},{"b":"12520","h":6628,"p":6650},{"b":"181","h":6591,"p":5328}]},"21599":{"reps":" قلت: هل سمعت من خليلك حديثا تحدثه؟ قال: نعم - سمعته","items":[{"b":"12520","h":6632,"p":6654},{"b":"181","h":6632,"p":5353}]},"21600":{"reps":" «من صلي علي جنازه فله قيراط، ومن انتظر حتي تدفن فله","items":[{"b":"12520","h":6640,"p":6661},{"b":"12520","h":6659,"p":6680},{"b":"181","h":6659,"p":5374},{"b":"748","h":9244,"p":2996}]},"21604":{"reps":" اني صائم، فلما كادوا ان يفرغوا جاء فجعل ياكل، فنظر القوم","items":[{"b":"12520","h":6650,"p":6671},{"b":"1733","h":13308,"p":15518},{"b":"1733","h":13309,"p":15519}]},"21616":{"reps":" سمعت ابا هريره، يقول لابن عباس: قال رسول الله ﷺ: «رؤيا","items":[{"b":"12520","h":6706,"p":6724},{"b":"181","h":6706,"p":5415}]},"21617":{"reps":" حدثني ابي العباس بن عبد المطلب قال: شهدت حنينا مع رسول","items":[{"b":"12520","h":6708,"p":6725},{"b":"181","h":6707,"p":5416}]},"21618":{"reps":" اخبرني نافع قال: سمعت العباس يقول للزبير: «يا ابا عبد الله،","items":[{"b":"12520","h":6711,"p":6728},{"b":"181","h":6710,"p":5421}]},"21628":{"reps":" كنت بين الحسين والحسن، ومروان يتشاتمان فجعل الحسن يكف الحسين، فقال","items":[{"b":"12520","h":6764,"p":6781},{"b":"181","h":6764,"p":5471},{"b":"98138","h":1177,"p":821}]},"21631":{"reps":" حج معاويه بن ابي سفيان، وحج معه معاويه بن حديج وكان","items":[{"b":"12520","h":6771,"p":6787},{"b":"1733","h":2758,"p":3302}]},"21632":{"reps":" قلت لعبيد الله بن ابي يزيد: رايت حسين بن علي؟ قال:","items":[{"b":"12520","h":6773,"p":6790},{"b":"43","h":11329,"p":5284}]},"21637":{"reps":" سمعت مورقا، عن عبد الله بن جعفر، ان رسول الله ﷺ","items":[{"b":"12520","h":6791,"p":6807},{"b":"181","h":6791,"p":5502}]},"21638":{"reps":" جاءت قريش الي ابي طالب فقالوا: ان ابن اخيك يؤذينا في","items":[{"b":"12520","h":6804,"p":6820},{"b":"181","h":6804,"p":5510},{"b":"1424","h":6610,"p":5009}]},"21640":{"reps":" سمعت ابن الزبير وهو يخطب قال: قال محمد ﵇: «من لبس","items":[{"b":"12520","h":6817,"p":6834},{"b":"181","h":6817,"p":5523}]},"21651":{"reps":" جاء عكاف بن وداعه الهلالي الي رسول الله ﷺ، فقال له","items":[{"b":"12520","h":6856,"p":6899},{"b":"748","h":5480,"p":1955}]},"21652":{"reps":" سمعت ضمره بن حبيب يقول: سمعت سلمه بن نفيل السكوني يقول:","items":[{"b":"12520","h":6861,"p":6908},{"b":"1424","h":8588,"p":6423}]},"21653":{"reps":" كانت همدان قد تحصنت في جبل - يقال له الحقل -","items":[{"b":"12520","h":6864,"p":6914},{"b":"181","h":6863,"p":5591}]},"21659":{"reps":" مر عثمان بن عفان - او عبد الرحمن بن عوف -","items":[{"b":"12520","h":6877,"p":6937},{"b":"654","h":293,"p":406}]},"21663":{"reps":" الله ﷺ: «لتنظر عدد الايام التي كانت تحيضهن قبل ان يكون","items":[{"b":"12520","h":6894,"p":6954},{"b":"181","h":6893,"p":5633}]},"21664":{"reps":" دخلت ام سليم الي رسول الله ﷺ فقالت: ان الله لا","items":[{"b":"12520","h":6895,"p":6955},{"b":"181","h":6894,"p":5634}]},"21667":{"reps":" سئلت عائشه، وام سلمه: اي العمل احب الي رسول الله ﷺ؟","items":[{"b":"12520","h":6905,"p":6965},{"b":"181","h":6904,"p":5651}]},"21669":{"reps":" كنت انا وميمونه عند النبي ﷺ، فجاء ابن ام مكتوم يستاذن،","items":[{"b":"12520","h":6922,"p":6980},{"b":"181","h":6921,"p":5667}]},"21672":{"reps":" والذي يحلف به ان كان علي لاقرب الناس عهدا برسول الله","items":[{"b":"12520","h":6934,"p":6992},{"b":"1424","h":4722,"p":3771}]},"21673":{"reps":" يا رسول الله، ابو الهيثم اتاك يتنجز عدته، فقال له النبي","items":[{"b":"12520","h":6942,"p":6999},{"b":"181","h":6942,"p":5690},{"b":"1424","h":5310,"p":4230}]},"21686":{"reps":" حدثني شهر بن حوشب قال: سالت ام سلمه قلت: يا ام","items":[{"b":"12520","h":6986,"p":7042},{"b":"181","h":6985,"p":5720}]},"21688":{"reps":" «ليس بك علي اهلك هوان، ان شئت سبعت لك، وان سبعت","items":[{"b":"12520","h":6996,"p":7052},{"b":"98138","h":1917,"p":1330},{"b":"1339","h":5608,"p":3957}]},"21692":{"reps":"دون ⦗٤٦٢⦘ السلمي قراءه عليه في غره شعبان سنه ثلاث وخمسين واربع","items":[{"b":"12520","h":7032,"p":7090},{"b":"1424","h":298,"p":414}]},"21695":{"reps":": حدثتني حفصه انه قال: قال النبي ﷺ: «ليؤمن هذا البيت جيش","items":[{"b":"12520","h":7043,"p":7101},{"b":"1339","h":2880,"p":2108}]},"21696":{"reps":" اربع لم يكن رسول الله ﷺ يدعهن: صيام العشر وعاشوراء، وصوم","items":[{"b":"12520","h":7048,"p":7105},{"b":"181","h":7047,"p":5767}]},"21701":{"reps":" رايت كان في بيتي طبقا من رسول الله ﷺ فجزعت من","items":[{"b":"12520","h":7074,"p":7133},{"b":"181","h":7074,"p":5781}]},"21703":{"reps":" كانت ميمونه تدان فتكثر فقال لها اهلها في ذلك ووجدوا عليها","items":[{"b":"12520","h":7083,"p":7144},{"b":"181","h":7082,"p":5788}]},"21704":{"reps":" اهدي لنا ضب، قالت: فاتاها رجلان من قومها فامرت به فصنع","items":[{"b":"12520","h":7084,"p":7145},{"b":"181","h":7084,"p":5792}]},"21706":{"reps":" قرات لعطاء كتابا معه، فاذا فيه: حدثتني ميمونه زوج النبي ﷺ:","items":[{"b":"12520","h":7094,"p":7156},{"b":"181","h":7094,"p":5802}]},"21710":{"reps":" ثقلت ميمونه زوج النبي ﷺ بمكه وليس عندها من بني اخيها،","items":[{"b":"12520","h":7110,"p":7172},{"b":"181","h":7109,"p":5811}]},"21712":{"reps":" حدثتني صفيه بنت حيي زوج النبي ﷺ، قالت: جئت الي النبي","items":[{"b":"12520","h":7121,"p":7184},{"b":"181","h":7121,"p":5824}]},"21714":{"reps":" حدثني ابو جعفر محمد بن علي، ونافع، ان عمرو بن نافع","items":[{"b":"12520","h":7129,"p":7193},{"b":"748","h":10088,"p":3214}]},"21721":{"reps":" حدثتني امي امينه، انها حدثتها امه الله بنت رزينه، عن امها","items":[{"b":"12520","h":7160,"p":7231},{"b":"181","h":7159,"p":5855}]},"21722":{"reps":" حدثتنا عليله بنت الكميت، قالت: سمعت امي امينه قالت: حدثتني امه","items":[{"b":"12520","h":7161,"p":7232},{"b":"181","h":7161,"p":5857},{"b":"1733","h":6736,"p":8316}]},"21724":{"reps":" خرجت في نسوه من بني سعد بن بكر نلتمس الرضعاء بمكه","items":[{"b":"12520","h":7163,"p":7235},{"b":"181","h":7162,"p":5857}]},"21726":{"reps":" حدثني عبد الحميد بن جعفر الانصاري، حدثنا ابو الابرد، مولي بني","items":[{"b":"12520","h":7172,"p":7247},{"b":"181","h":7171,"p":5869}]},"21727":{"reps":" لما اراد معاويه ان يستخلف يزيد بعث الي عامل المدينه ان","items":[{"b":"12520","h":7174,"p":7251},{"b":"181","h":7173,"p":5871}]},"21728":{"reps":" دخل عمرو بن حزم علي عمرو بن العاص فقال: قتل عمار،","items":[{"b":"12520","h":7175,"p":7252},{"b":"12520","h":7346,"p":7429},{"b":"181","h":7346,"p":6005}]},"21730":{"reps":" ان الناس يزعمون انك لا تغضب لبناتك، وهذا علي ناكح ابنه","items":[{"b":"12520","h":7181,"p":7262},{"b":"181","h":7181,"p":5880}]},"21733":{"reps":" اخبرت، ان النبي ﷺ قال: «لا تسبوا خالدا، فانه سيف من","items":[{"b":"12520","h":7188,"p":7271},{"b":"181","h":7188,"p":5886}]},"21734":{"reps":" انطلقت انا وسهل بن حنيف نلتمس الخمر، فوجدنا خمرا وغديرا، وكان","items":[{"b":"12520","h":7195,"p":7279},{"b":"181","h":7195,"p":5893}]},"21736":{"reps":" كان عبد الرحمن بن عوف «اذا دخل منزله قرا في زوايا","items":[{"b":"12520","h":7207,"p":7292},{"b":"1424","h":6113,"p":4771}]},"21737":{"reps":" «يا رسول الله، اخيت بيني وبين حمزه بن عبد المطلب» [حكم","items":[{"b":"12520","h":7210,"p":7296},{"b":"12520","h":7211,"p":7297},{"b":"1733","h":2927,"p":3492}]},"21740":{"reps":" ايكم القائل كلمه كذا وكذا؟ فارم القوم مرتين، قال: فلعلك يا","items":[{"b":"12520","h":7224,"p":7312},{"b":"181","h":7223,"p":5918}]},"21741":{"reps":" حدثنا عبد الغفار بن القاسم، عن اياد بن لقيط، عن قرظه","items":[{"b":"12520","h":7228,"p":7316},{"b":"181","h":7228,"p":5925}]},"21743":{"reps":" فقال ابو برده، فقال ابو موسي: وكان رسول الله ﷺ يقول:","items":[{"b":"12520","h":7233,"p":7319},{"b":"654","h":936,"p":1251},{"b":"28107","h":287,"p":704}]},"21745":{"reps":" اقبلت الي رسول الله ﷺ انا ورجلان من الاشعريين: احدهما عن","items":[{"b":"12520","h":7240,"p":7326},{"b":"181","h":7239,"p":5932}]},"21747":{"reps":" كان النبي ﷺ يسمي لنا نفسه اسماء، فقال: «انا محمد، واحمد،","items":[{"b":"12520","h":7244,"p":7330},{"b":"181","h":7244,"p":5935},{"b":"1424","h":4800,"p":3837},{"b":"1424","h":7258,"p":5473}]},"21748":{"reps":" حدث ابو موسي وهو بالدير من اصبهان قال: قال رسول الله","items":[{"b":"12520","h":7247,"p":7333},{"b":"181","h":7247,"p":5938}]},"21750":{"reps":" قدم علي عمر، فقام علي بابه فقال ⦗٢٤١⦘: السلام عليكم ورحمه","items":[{"b":"12520","h":7257,"p":7344},{"b":"181","h":7257,"p":5949},{"b":"1733","h":863,"p":1020}]},"21754":{"reps":" كنت انا وابو الدرداء عند رسول الله ﷺ فقال: «من حفظ","items":[{"b":"12520","h":7275,"p":7359},{"b":"181","h":7275,"p":5960},{"b":"748","h":5755,"p":2033},{"b":"1424","h":8262,"p":6184}]},"21757":{"reps":" «يا ابا موسي مررت بك البارحه ومعي عائشه، وانت تقرا في","items":[{"b":"12520","h":7279,"p":7363},{"b":"181","h":7278,"p":5963}]},"21762":{"reps":" «مثل البيت الذي يذكر الله فيه، والبيت الذي لا يذكر الله","items":[{"b":"12520","h":7306,"p":7390},{"b":"181","h":7305,"p":5978}]},"21766":{"reps":" لما فرغ رسول الله ﷺ من حنين بعث ابا عامر علي","items":[{"b":"12520","h":7313,"p":7397},{"b":"1424","h":4966,"p":3973},{"b":"1424","h":5025,"p":4023},{"b":"98138","h":2960,"p":2099}]},"21769":{"reps":" سمعت عمرو بن العاص يقول: قال رسول الله ﷺ: «اشدد عليك","items":[{"b":"12520","h":7336,"p":7419},{"b":"181","h":7335,"p":5992}]},"21771":{"reps":" خرجنا مع عمرو بن العاص متوجهين الي مكه، فاذا نحن بامراه","items":[{"b":"12520","h":7343,"p":7426},{"b":"181","h":7342,"p":6002}]},"21773":{"reps":" رجعت مع معاويه من صفين فكان معاويه وابو الاعور السلمي يسيرون","items":[{"b":"12520","h":7351,"p":7434},{"b":"181","h":7351,"p":6007}]},"21774":{"reps":" استاذن جعفر رسول الله ﷺ فقال: ائذن لي ان اتي ارضا","items":[{"b":"12520","h":7352,"p":7435},{"b":"181","h":7352,"p":6008}]},"21775":{"reps":" قال عمرو بن العاص: خرج جيش من المسلمين انا اميرهم حتي","items":[{"b":"12520","h":7353,"p":7436},{"b":"1424","h":5781,"p":4566}]},"21778":{"reps":" وجدت في كتابي، عن سويد ولم ار عليه علامه السماع ,","items":[{"b":"12520","h":7382,"p":7464},{"b":"181","h":7381,"p":6031}]},"21783":{"reps":" «لا حلف في الاسلام، وايما حلف كان في الجاهليه فان الاسلام","items":[{"b":"12520","h":7406,"p":7490},{"b":"181","h":7406,"p":6049},{"b":"1733","h":1580,"p":1903}]},"21784":{"reps":" واخبرنا عمرو بن دينار، عن نافع بن جبير، عن ابيه، ان","items":[{"b":"12520","h":7410,"p":7493},{"b":"181","h":7408,"p":6052}]},"21789":{"reps":" سمعت ابا برزه يحدث، قال: بعث رسول الله ﷺ الي احياء","items":[{"b":"12520","h":7432,"p":7514},{"b":"181","h":7431,"p":6069}]},"21790":{"reps":" حدثتنا ام الاسود بنت يزيد، مولي ابي برزه الاسلمي، قالت: حدثتني","items":[{"b":"12520","h":7439,"p":7519},{"b":"181","h":2816,"p":2460}]},"21791":{"reps":" مات بغل عند رجل , فاتي رسول الله ﷺ يستفتيه، قال:","items":[{"b":"12520","h":7445,"p":7529},{"b":"1733","h":1977,"p":2358}]},"21792":{"reps":" «كان بلال يؤذن الظهر اذا دحضت الشمس، وكان ربما اخر الاقامه","items":[{"b":"12520","h":7450,"p":7534},{"b":"1733","h":1947,"p":2326}]},"21795":{"reps":" كتبت الي جابر بن سمره مع غلامي نافع اخبرني بشيء سمعته","items":[{"b":"12520","h":7463,"p":7547},{"b":"181","h":7462,"p":6094},{"b":"1733","h":1809,"p":2177}]},"21802":{"reps":" تدانيت النبي ﷺ بمسجد ⦗٤٧٧⦘ الخيف، فقال لي اصحابه: اليك يا","items":[{"b":"12520","h":7492,"p":7577},{"b":"181","h":7491,"p":6109}]},"21803":{"reps":" ذكرنا احب الاعمال الي الله، فقلنا: من يسال لنا رسول الله","items":[{"b":"12520","h":7499,"p":7585},{"b":"181","h":7498,"p":6117}]},"21804":{"reps":" «صيام ثلاثه ايام من كل شهر صيام الدهر، ايام البيض صبيحه","items":[{"b":"12520","h":7504,"p":7591},{"b":"1733","h":2499,"p":3010},{"b":"748","h":3853,"p":1472}]},"21805":{"reps":"ان النبي ﷺ مر علي نسوه , فسلم عليهن» [حكم حسين سليم","items":[{"b":"12520","h":7506,"p":7593},{"b":"1733","h":2486,"p":2992},{"b":"654","h":4795,"p":6491}]},"21806":{"reps":" «ما من قوم يكون بين ظهرانيهم رجل يعمل بالمعاصي هم امنع","items":[{"b":"12520","h":7508,"p":7595},{"b":"1733","h":2380,"p":2880}]},"21807":{"reps":" سمعت جرير بن عبد الله، حين مات المغيره بن شعبه، واستعمل","items":[{"b":"12520","h":7509,"p":7596},{"b":"1733","h":2220,"p":2675},{"b":"1733","h":2437,"p":2937},{"b":"1733","h":2457,"p":2957},{"b":"1733","h":2463,"p":2966},{"b":"1733","h":2467,"p":2970},{"b":"1733","h":2473,"p":2976},{"b":"1733","h":2480,"p":2983},{"b":"748","h":5264,"p":1898},{"b":"748","h":8417,"p":2790}]},"21810":{"reps":" سمعته يحدث ان امراه جاءت الي النبي ﷺ , فوهبت نفسها","items":[{"b":"12520","h":7521,"p":7609},{"b":"181","h":7520,"p":6133}]},"21811":{"reps":" في القوم: كنت عند رسول الله ﷺ , فقامت امراه، فقالت:","items":[{"b":"12520","h":7522,"p":7610},{"b":"181","h":7522,"p":6134}]},"21813":{"reps":" حدثني ابي، عن قدامه بن ابراهيم، قال: رايت الحجاج يضرب عباس","items":[{"b":"12520","h":7532,"p":7620},{"b":"181","h":7532,"p":6143}]},"21818":{"reps":" «كن النساء يؤمرن في عهد رسول الله ﷺ في الصلاه ان","items":[{"b":"12520","h":7542,"p":7630},{"b":"181","h":7542,"p":6148}]},"21819":{"reps":" الله ﷺ لبعض اصحابه: «اذهبوا بنا لنصلح بينهم» فخرج وخرج معه","items":[{"b":"12520","h":7545,"p":7633},{"b":"181","h":3429,"p":2835}]},"21827":{"reps":" يا رسول الله، كنت عند ابن عم لي البارحه، فلان، وهو","items":[{"b":"181","h":69,"p":108},{"b":"1733","h":10128,"p":12129}]},"21830":{"reps":" سمعت ابا كبشه الانماري، وكان له صحبه يحدث: عن ابي بكر","items":[{"b":"181","h":73,"p":111},{"b":"1424","h":1743,"p":1451},{"b":"1424","h":2588,"p":2154},{"b":"1424","h":7708,"p":5773},{"b":"1363","h":822,"p":1013},{"b":"654","h":1862,"p":2463},{"b":"907","h":1403,"p":1845},{"b":"1339","h":2241,"p":1657},{"b":"1339","h":2249,"p":1662},{"b":"1339","h":4597,"p":3336}]},"21844":{"reps":" ان رواته مجاهيل\". = الصديق، قال: قال رسول الله ﷺ: \"ان","items":[{"b":"181","h":111,"p":150},{"b":"1424","h":6990,"p":5273},{"b":"1363","h":2729,"p":2402},{"b":"117359","h":4877,"p":4128}]},"21846":{"reps":" \"جاءت الجده الي ابي بكر الصديق تساله ميراثها، فقال لها ابو","items":[{"b":"181","h":119,"p":156},{"b":"28107","h":1870,"p":2287}]},"21853":{"reps":"من طرق عن ابن عيينه عن عمرو بن دينار عن يحيي بن","items":[{"b":"181","h":135,"p":170},{"b":"181","h":4712,"p":3909},{"b":"181","h":5869,"p":4769},{"b":"181","h":6948,"p":5695},{"b":"748","h":3608,"p":1387},{"b":"748","h":3634,"p":1395},{"b":"748","h":3955,"p":1501},{"b":"1363","h":649,"p":863},{"b":"1363","h":1541,"p":1582},{"b":"98138","h":3227,"p":2292},{"b":"98139","h":354,"p":313},{"b":"98139","h":7135,"p":3332},{"b":"1339","h":3664,"p":2727},{"b":"1339","h":4364,"p":3191}]},"21860":{"reps":" \"ان الميت يعذب في قبره ما نيح عليه\".P\u0016= وقد توبع عبيد","items":[{"b":"181","h":155,"p":188},{"b":"181","h":156,"p":189},{"b":"181","h":3726,"p":3069},{"b":"181","h":5238,"p":4340},{"b":"1363","h":1026,"p":1168}]},"21866":{"reps":" اللهم اني اشهدك علي امراء الامصار، فانما بعثتهم ليعلموهم دينهم، وسنه","items":[{"b":"181","h":184,"p":216},{"b":"748","h":5964,"p":2083}]},"21870":{"reps":" \"رواه احمد وابو يعلي وفيه راو لم يسم، وبقيه رجاله ثقات\".","items":[{"b":"181","h":192,"p":221},{"b":"181","h":2216,"p":1886},{"b":"98139","h":649,"p":446},{"b":"98139","h":778,"p":502},{"b":"98139","h":785,"p":506},{"b":"98139","h":1460,"p":775},{"b":"98139","h":1696,"p":885},{"b":"98139","h":2553,"p":1273},{"b":"98139","h":2897,"p":1394},{"b":"98139","h":3951,"p":1772},{"b":"98139","h":4072,"p":1810},{"b":"98139","h":4624,"p":2009},{"b":"98139","h":5846,"p":2500},{"b":"98139","h":5879,"p":2513},{"b":"98139","h":5987,"p":2564}]},"21878":{"reps":" خرجت مع عمر بن الخطاب الي مكه، فاستقبلنا امير مكه نافع","items":[{"b":"181","h":211,"p":240},{"b":"1733","h":7297,"p":9003},{"b":"748","h":3269,"p":1261},{"b":"1376","h":4160,"p":6119},{"b":"907","h":2010,"p":2580},{"b":"28107","h":154,"p":571},{"b":"28107","h":378,"p":795}]},"21896":{"reps":" عن الوليد بن ابي الوليد باسناده به ... ولم يذكر فيه","items":[{"b":"181","h":253,"p":276},{"b":"181","h":1900,"p":1652},{"b":"748","h":2010,"p":881}]},"21901":{"reps":"السنه\" [رقم ٢٨٦]، والبيهقي [رقم ١٣٢١٦]، وابن سعد في \"الطبقات\" [٨/ ١٥٩]،","items":[{"b":"181","h":265,"p":286},{"b":"181","h":5162,"p":4295},{"b":"181","h":5202,"p":4317},{"b":"98139","h":1350,"p":716}]},"21919":{"reps":"اسناد ضعيف لا يثبت. وابن ابي ليلي: امام فقيه عالم كبير جليل","items":[{"b":"181","h":306,"p":320},{"b":"748","h":3592,"p":1381},{"b":"117359","h":3099,"p":2601},{"b":"98139","h":4750,"p":2059}]},"21942":{"reps":" والقطيعي في الالف دينار [رقم ٣٨]، والبيهقي [٢٠٠٠]، والطحاوي في \"شرح","items":[{"b":"181","h":386,"p":386},{"b":"181","h":415,"p":407},{"b":"181","h":456,"p":434},{"b":"181","h":496,"p":475},{"b":"181","h":1739,"p":1518},{"b":"181","h":2420,"p":2077},{"b":"181","h":6379,"p":5155},{"b":"748","h":7011,"p":2350}]},"21943":{"reps":"رق عن ابي اسحاق السبيعي عن هانئ بن هانئ عن علي به","items":[{"b":"181","h":403,"p":397},{"b":"181","h":5068,"p":4211},{"b":"748","h":11109,"p":3482}]},"21951":{"reps":" فاغتسلت، ثم اتيته، فدعا لي بدعوات ما يسرني ان لي بها","items":[{"b":"181","h":424,"p":411},{"b":"748","h":2425,"p":998},{"b":"1424","h":3233,"p":2618}]},"21952":{"reps":" اتي النبي ﷺ بلحم صيد وهو محرم، فلم ياكله. ٤٣٤ -","items":[{"b":"181","h":433,"p":417},{"b":"98138","h":3091,"p":2191},{"b":"98139","h":830,"p":527}]},"22000":{"reps":": القائل الفاحشه والذي يسمع في الاثم سواء. ٥٥٤ - حدثنا عبد","items":[{"b":"181","h":553,"p":530},{"b":"7895","h":795,"p":1350},{"b":"654","h":2805,"p":3832}]}}